myzoom
