Metadata-Version: 2.1
Name: add-registrant-zoom
Version: 0.3
Summary: A package for interacting with Zoom API
Home-page: https://github.com/own-coder/add-zoom-registrant
Author: Mangesh Chavan
Author-email: chavanmangesh245@gmail.com
Classifier: License :: OSI Approved :: MIT License
Classifier: Programming Language :: Python :: 3.7
Classifier: Programming Language :: Python :: 3.8
Classifier: Programming Language :: Python :: 3.10
